publish_npm.py
publish_npm-1.2.0.dist-info/entry_points.txt
publish_npm-1.2.0.dist-info/WHEEL
publish_npm-1.2.0.dist-info/METADATA
publish_npm-1.2.0.dist-info/RECORD
